CHANGES.txt
LICENSE.txt
README.txt
setup.py
version.txt
haufe/__init__.py
haufe.stripml.egg-info/PKG-INFO
haufe.stripml.egg-info/SOURCES.txt
haufe.stripml.egg-info/dependency_links.txt
haufe.stripml.egg-info/namespace_packages.txt
haufe.stripml.egg-info/not-zip-safe
haufe.stripml.egg-info/requires.txt
haufe.stripml.egg-info/top_level.txt
haufe/stripml/README.txt
haufe/stripml/__init__.py
haufe/stripml/stripml.cpp
haufe/stripml/tests.py