Metadata-Version: 1.0
Name: haufe.stripml
Version: 1.2.1
Summary: Python extension for removing markup from strings.
Home-page: http://pypi.python.org/pypi/haufe.stripml
Author: Tobias Rodaebel
Author-email: rodaebel@users.sourceforge.net
License: LGPL 3
Keywords: SGML,HTML,XML,XHTML
Platform: All
Classifier: Development Status :: 5 - Production/Stable
Classifier: License :: OSI Approved :: GNU Library or Lesser General Public License (LGPL)
Classifier: Intended Audience :: Developers
Classifier: Operating System :: OS Independent
Classifier: Programming Language :: Python
Classifier: Programming Language :: C++
Classifier: Topic :: Software Development :: Libraries :: Python Modules
Classifier: Topic :: Text Processing :: Markup :: HTML
Classifier: Topic :: Text Processing :: Markup :: SGML
Classifier: Topic :: Text Processing :: Markup :: XML
